great_tool/__init__.py
great_tool/functions.py
great_tool_chrisfork-0.0.5.dist-info/LICENSE
great_tool_chrisfork-0.0.5.dist-info/METADATA
great_tool_chrisfork-0.0.5.dist-info/WHEEL
great_tool_chrisfork-0.0.5.dist-info/top_level.txt
great_tool_chrisfork-0.0.5.dist-info/RECORD
